stagecam/__init__.py
stagecam/face_tracker.py
stagecam/frame_transformer.py
stagecam/show.py
stagecam/stagecam.py
stagecam-0.1.0.dist-info/METADATA
stagecam-0.1.0.dist-info/WHEEL
stagecam-0.1.0.dist-info/top_level.txt
stagecam-0.1.0.dist-info/RECORD
