Metadata-Version: 2.4
Name: stagecam
Version: 0.1.0
Summary: A Python library for face-aware frame tracking like Apple Center Stage
Home-page: https://github.com/K-Rutuparna1087/StageCam
Author: K Rutuparna
License: MIT
Classifier: Development Status :: 3 - Alpha
Classifier: Intended Audience :: Developers
Classifier: License :: OSI Approved :: MIT License
Classifier: Programming Language :: Python :: 3
Classifier: Operating System :: OS Independent
Requires-Python: >=3.7
Requires-Dist: opencv-python
Requires-Dist: mediapipe
Requires-Dist: numpy
Dynamic: author
Dynamic: classifier
Dynamic: description
Dynamic: description-content-type
Dynamic: home-page
Dynamic: license
Dynamic: requires-dist
Dynamic: requires-python
Dynamic: summary
